{
    "CacheContainer": {
        "CacheType": "WIKIPEDIAMLB1936ALLSTARSUPPLEMENT", 
        "CachedOn": "2021-12-14T15:28:44", 
        "ExpiresOn": "2022-12-14T15:28:44", 
        "Version": "0"
    }, 
    "Items": [
        {
            "1": {}, 
            "2": {
                "awayTeam": "American League", 
                "caption": "1936 Major League Baseball All-Star Game", 
                "date": "1936-07-07", 
                "description": "The umpires rotated positions clockwise in the middle of the fifth inning, with Summers moving behind the plate.", 
                "homeTeam": "National League", 
                "inspected:Attendance": "25,556", 
                "inspected:Ceremonial first pitch": "None", 
                "inspected:City": "Boston, Massachusetts", 
                "inspected:Date": "July 7, 1936", 
                "inspected:Managers": "Joe McCarthy (NYY)Charlie Grimm (CHC)", 
                "inspected:Radio": "Mutual, CBS, NBC", 
                "inspected:Radio announcers": "Fred Hoey, Linus Travers (Mutual)Arch McDonald, Dolly Stark (CBS)Hal Totten, Tom Manning, Graham McNamee (NBC)", 
                "inspected:Venue": "National League Park"
            }
        }
    ]
}